Metadata-Version: 2.1
Name: acquabr
Version: 0.1.1
Summary: Python Library for Hydrological Analysis in Brazil
Author: Leonardo Maciel de Sousa
Author-email: leonardo.maciel3@academico.ufpb.br
Keywords: hydrology,hydrological analysis,rainfall data Brazil,flow data Brazil,HIDROWEB,rainfall analysis,flow analysis,Brazil rainfall,Brazil flow 
Classifier: Programming Language :: Python :: 3
Classifier: License :: OSI Approved :: MIT License
Classifier: Operating System :: OS Independent
Classifier: Topic :: Scientific/Engineering :: Hydrology
Requires-Python: >=3.6
Provides-Extra: dev
License-File: LICENCE
